{
  "dataset": {
    "N": 10000000,
    "alpha": 0.7,
    "target_alpha": 0.7,
    "minority_dist": "unique",
    "seed": 42
  },
  "results": [
    {
      "method": "hash_table",
      "construction_time_s": 2.5262340829940513,
      "avg_inference_time_ns": 7086.62,
      "memory_bytes": 554058856,
      "filter_params": null,
      "filter_type": null
    },
    {
      "method": "csf_filter_optimal_binary_fuse",
      "construction_time_s": 7.399271667003632,
      "avg_inference_time_ns": 378.84,
      "memory_bytes": 22596505,
      "filter_params": {
        "fingerprint_bits": 1
      },
      "filter_type": "binary_fuse"
    },
    {
      "method": "csf_filter_shibuya_binary_fuse",
      "construction_time_s": 6.824192125000991,
      "avg_inference_time_ns": 437.87,
      "memory_bytes": 22870931,
      "filter_params": {
        "fingerprint_bits": 3,
        "epsilon": 0.125,
        "epsilon_star": 0.10766171356120627
      },
      "filter_type": "binary_fuse"
    }
  ]
}